{
  "system_name": "LuvOnPurpose Sovereign System",
  "version": "Phase I + System File Standard v1",
  "status": "Active - Multi-Workstream",
  "last_updated": "2025-09-26",
  "core_pillars": [
    {
      "name": "Sovereign System Build",
      "description": "Core infrastructure and legal foundation",
      "workstreams": [
        "Build_Luv_System",
        "Eternal_Flame_Vault",
        "House_Record_Chamber"
      ],
      "components": [
        "Legal entity documentation",
        "System architecture",
        "Court filing profiles",
        "Archival systems"
      ]
    },
    {
      "name": "Legal & Probate Case",
      "description": "Case management and legal proceedings",
      "workstreams": [
        "Case_Against_Hebrews"
      ],
      "components": [
        "Case petitions",
        "Evidence exhibits (A-Z)",
        "Court profiles",
        "Probate integration",
        "Affidavits and certifications"
      ]
    },
    {
      "name": "Education & Academy",
      "description": "Curriculum and educational programs",
      "workstreams": [
        "Luv_Academy"
      ],
      "components": [
        "Finance curriculum",
        "Law curriculum",
        "Contracting curriculum",
        "Music & Art curriculum",
        "Transportation curriculum",
        "Course materials",
        "Educational exhibits"
      ]
    },
    {
      "name": "Grant & Funding",
      "description": "Grant packages and funding applications",
      "workstreams": [
        "Grant_Packages"
      ],
      "components": [
        "Grant checklists",
        "Grant narratives",
        "Budget templates",
        "Supporting documentation",
        "Funder profiles"
      ]
    }
  ],
  "execution_modules": [
    {
      "id": 1,
      "name": "Token Chain Validation",
      "layer": "Token & Activation",
      "function": "Enforces sequential token activation (MIRROR \u2192 GIFT \u2192 SPARK \u2192 HOUSE)",
      "status": "\u2705 Active"
    },
    {
      "id": 2,
      "name": "Gift Token Unlock Timer",
      "layer": "Token & Activation",
      "function": "Manages gift token unlocking via time or task completion",
      "status": "\u2705 Active"
    },
    {
      "id": 3,
      "name": "Tokenized Receipt Generator",
      "layer": "Financial & Payment",
      "function": "Generates cryptographic receipts for payments",
      "status": "\u2705 Active"
    },
    {
      "id": 4,
      "name": "House Activation Validator",
      "layer": "Validation & Verification",
      "function": "Validates all conditions for House activation and Crown issuance",
      "status": "\u2705 Active"
    },
    {
      "id": 5,
      "name": "Offline Companion System",
      "layer": "Resilience & Recovery",
      "function": "Enables offline operation and data recovery",
      "status": "\u2705 Active"
    }
  ],
  "system_architecture": {
    "token_layer": {
      "name": "Token & Activation Layer",
      "purpose": "Manages token lifecycle and House activation sequences",
      "key_tokens": [
        "MIRROR",
        "GIFT",
        "SPARK",
        "HOUSE",
        "CROWN"
      ]
    },
    "financial_layer": {
      "name": "Financial & Payment Layer",
      "purpose": "Handles payments, receipts, and financial tracking",
      "key_features": [
        "Crypto payments",
        "Receipt generation",
        "Transaction logging"
      ]
    },
    "validation_layer": {
      "name": "Validation & Verification Layer",
      "purpose": "Ensures system integrity and activation requirements",
      "key_checks": [
        "Scroll sealing",
        "Token sequences",
        "LuvLedger status",
        "GPT readiness"
      ]
    },
    "resilience_layer": {
      "name": "Resilience & Recovery Layer",
      "purpose": "Maintains availability and data integrity",
      "key_features": [
        "Offline operation",
        "Local backups",
        "Sync recovery"
      ]
    },
    "legal_layer": {
      "name": "Legal & Governance Layer",
      "purpose": "Manages legal entities, court filings, and compliance",
      "key_components": [
        "Entity documentation",
        "Case management",
        "Court profiles"
      ]
    },
    "education_layer": {
      "name": "Education & Development Layer",
      "purpose": "Provides curriculum and learning materials",
      "key_components": [
        "Finance",
        "Law",
        "Contracting",
        "Arts",
        "Transportation"
      ]
    },
    "funding_layer": {
      "name": "Funding & Grants Layer",
      "purpose": "Manages grant applications and funding packages",
      "key_components": [
        "Grant templates",
        "Narratives",
        "Budgets",
        "Funder profiles"
      ]
    }
  },
  "file_architecture": {
    "structure": {
      "00_Root": "Immutable originals and seed documents",
      "01_Working": "Active duplicates with versioning",
      "02_Exhibits": "Supporting documentation and evidence",
      "03_Signatures": "Approvals and execution bundles",
      "04_Final": "Finalized and court-ready documents",
      "05_Archive": "Local archival copies",
      "Court_Profiles": "Venue and funder-specific preferences"
    },
    "global_archives": {
      "Eternal_Flame_Vault": "Sealed finals across all workstreams",
      "House_Record_Chamber": "Permanent reference copies"
    }
  },
  "activation_flow": {
    "step_1": "Token Chain Validation - Verify sequential activation",
    "step_2": "Scrolls Sealed - Confirm all documentation complete",
    "step_3": "LuvLedger Activation - Initialize financial tracking",
    "step_4": "House Activation Validator - Check all conditions",
    "step_5": "Crown of Completion - Issue upon success",
    "step_6": "Archival - Store in Eternal Flame Vault"
  },
  "key_concepts": {
    "sovereign_system": "Self-governing system with built-in legal and financial frameworks",
    "token_sequence": [
      "MIRROR",
      "GIFT",
      "SPARK",
      "HOUSE"
    ],
    "crown_of_completion": "Issued upon successful House activation",
    "eternal_flame_vault": "Immutable archive for sealed documents",
    "house_record_chamber": "Permanent reference system",
    "probate_integration": "Court-ready case management and exhibits"
  }
}